[
    {
        "taskId":"TASK-0",
        "taskName":"TASKNAME1",
        "taskAssigne":"000",
        "taskCreator":"000",
        "tiedToProj":"PROJ0",
        "commentsAdded":["DEMOCOMMENT"],
        "status":"DONE"
    },
    {
        "taskId":"TASK-1",
        "taskName":"TASKNAME1",
        "taskAssigne":"002",
        "taskCreator":"002",
        "tiedToProj":"Proj1",
        "commentsAdded":["DEMOCOMMENT"],
        "status":"Completed"
    },
    {
        "taskId":"TASK-3",
        "taskName":"TASKNAME1",
        "taskAssigne":"003",
        "taskCreator":"002",
        "tiedToProj":"PROJ1",
        "commentsAdded":[],
        "status":"Active"
    }
]